src/__init__.py
src/layers.py
src/loggingin.py
src/speedfilein.py
src/tensorclass.py
pythonlibtest201-0.0.1.dist-info/METADATA
pythonlibtest201-0.0.1.dist-info/WHEEL
pythonlibtest201-0.0.1.dist-info/top_level.txt
pythonlibtest201-0.0.1.dist-info/RECORD
